odoo/addons/mail_activity_chatter/CHANGELOG.md
odoo/addons/mail_activity_chatter/README.rst
odoo/addons/mail_activity_chatter/__init__.py
odoo/addons/mail_activity_chatter/__manifest__.py
odoo/addons/mail_activity_chatter/models/__init__.py
odoo/addons/mail_activity_chatter/models/mail_activity.py
odoo/addons/mail_activity_chatter/static/description/icon.png
odoo/addons/mail_activity_chatter/static/src/xml/mail_chatter_buttons.xml
odoo/addons/mail_activity_chatter/views/mail_activity_views.xml
odoo12_addon_mail_activity_chatter-12.0.0.1.0.dist-info/METADATA
odoo12_addon_mail_activity_chatter-12.0.0.1.0.dist-info/WHEEL
odoo12_addon_mail_activity_chatter-12.0.0.1.0.dist-info/top_level.txt
odoo12_addon_mail_activity_chatter-12.0.0.1.0.dist-info/RECORD
