Metadata-Version: 2.1
Name: odoo12-addon-mail-activity-chatter
Version: 12.0.0.1.0
Summary: Adds the chatter functionality in mail activities so notes can be left on them.
Home-page: https://gitlab.com/somitcoop/erp-research/odoo-helpdesk
Author: Som It Cooperatiu SCCL, Som Connexió SCCL, Odoo Community Association (OCA)",
Author-email: support@odoo-community.org
License: AGPL-3
Classifier: Programming Language :: Python
Classifier: Framework :: Odoo
Classifier: Framework :: Odoo :: 12.0
Classifier: License :: OSI Approved :: GNU Affero General Public License v3
Requires-Python: >=3.5
Requires-Dist: odoo12-addon-mail-activity-board
Requires-Dist: odoo <12.1dev,>=12.0a
